odoo10_addon_sale_order_line_confirmation_date-10.0.1.0.1-nspkg.pth
odoo/addons/sale_order_line_confirmation_date/README.rst
odoo/addons/sale_order_line_confirmation_date/__init__.py
odoo/addons/sale_order_line_confirmation_date/__manifest__.py
odoo/addons/sale_order_line_confirmation_date/hooks.py
odoo/addons/sale_order_line_confirmation_date/i18n/sale_order_line_confirmation_date.pot
odoo/addons/sale_order_line_confirmation_date/models/__init__.py
odoo/addons/sale_order_line_confirmation_date/models/sale_order_line.py
odoo/addons/sale_order_line_confirmation_date/readme/CONTRIBUTORS.rst
odoo/addons/sale_order_line_confirmation_date/readme/DESCRIPTION.rst
odoo/addons/sale_order_line_confirmation_date/static/description/icon.png
odoo/addons/sale_order_line_confirmation_date/static/description/index.html
odoo10_addon_sale_order_line_confirmation_date-10.0.1.0.1.dist-info/METADATA
odoo10_addon_sale_order_line_confirmation_date-10.0.1.0.1.dist-info/WHEEL
odoo10_addon_sale_order_line_confirmation_date-10.0.1.0.1.dist-info/namespace_packages.txt
odoo10_addon_sale_order_line_confirmation_date-10.0.1.0.1.dist-info/top_level.txt
odoo10_addon_sale_order_line_confirmation_date-10.0.1.0.1.dist-info/RECORD
